apitask/__init__.py
apitask/http_api.py
apitask/ip_generator.py
apitask/main.py
apitask/tcp_server_code.py
apitask/udp_client.py
apitask/udp_server_code.py
apitask/xmlrpc_client_code.py
apitask/xmlrpc_server_code.py
apiinteractive-0.0.1.dist-info/METADATA
apiinteractive-0.0.1.dist-info/WHEEL
apiinteractive-0.0.1.dist-info/top_level.txt
apiinteractive-0.0.1.dist-info/RECORD
