Metadata-Version: 2.1
Name: apiinteractive
Version: 0.0.1
Summary: A package for accessing various APIs.
Project-URL: Source, https://github.com/AlpeshThamke/api_tasks
